DEM_lib/DEMO.py
DEM_lib/__init__.py
DEM_lib-0.1.dist-info/LICENSE
DEM_lib-0.1.dist-info/METADATA
DEM_lib-0.1.dist-info/WHEEL
DEM_lib-0.1.dist-info/top_level.txt
DEM_lib-0.1.dist-info/RECORD
