Metadata-Version: 2.2
Name: DEM_lib
Version: 0.1
Summary: Simple
Author: DEOM
Author-email: tvvvyvv@gmail.com
Classifier: Programming Language :: Python :: 3
Classifier: License :: OSI Approved :: MIT License
Classifier: Operating System :: OS Independent
License-File: LICENSE
Dynamic: author
Dynamic: author-email
Dynamic: classifier
Dynamic: summary
